tabmemcheck/__init__.py
tabmemcheck/analysis.py
tabmemcheck/chat_completion.py
tabmemcheck/cli_interface.py
tabmemcheck/datasets.py
tabmemcheck/functions.py
tabmemcheck/llm.py
tabmemcheck/row_independence.py
tabmemcheck/tests.py
tabmemcheck/utils.py
tabmemcheck/version.py
tabmemcheck/datasets/__init__.py
tabmemcheck/datasets/load.py
tabmemcheck/datasets/transform.py
tabmemcheck/resources/__init__.py
tabmemcheck/resources/system-prompts.yaml
tabmemcheck/resources/config/__init__.py
tabmemcheck/resources/config/system-prompts.yaml
tabmemcheck/resources/config/transform/__init__.py
tabmemcheck/resources/config/transform/acs-income.yaml
tabmemcheck/resources/config/transform/acs-travel.yaml
tabmemcheck/resources/config/transform/adult.yaml
tabmemcheck/resources/config/transform/california-housing.yaml
tabmemcheck/resources/config/transform/fico.yaml
tabmemcheck/resources/config/transform/icu.yaml
tabmemcheck/resources/config/transform/iris.yaml
tabmemcheck/resources/config/transform/openml-diabetes.yaml
tabmemcheck/resources/config/transform/spaceship-titanic.yaml
tabmemcheck/resources/config/transform/titanic.yaml
tabmemcheck/resources/config/transform/wine.yaml
tabmemcheck/resources/csv/__init__.py
tabmemcheck/resources/csv/adult-train.csv
tabmemcheck/resources/csv/california-housing.csv
tabmemcheck/resources/csv/iris.csv
tabmemcheck/resources/csv/openml-diabetes.csv
tabmemcheck/resources/csv/titanic-train.csv
tabmemcheck/resources/csv/uci-wine.csv
tabmemcheck-0.1.6.dist-info/LICENSE
tabmemcheck-0.1.6.dist-info/METADATA
tabmemcheck-0.1.6.dist-info/WHEEL
tabmemcheck-0.1.6.dist-info/top_level.txt
tabmemcheck-0.1.6.dist-info/RECORD
