Metadata-Version: 2.1
Name: tabmemcheck
Version: 0.1.6
Summary: Testing Language Models for Memorization of Tabular Data
Home-page: https://github.com/interpretml/LLM-Tabular-Memorization-Checker
Author: Sebastian Bordt, Harsha Nori, Rich Caruana
Author-email: sbordt@posteo.de
Classifier: Programming Language :: Python :: 3
Classifier: License :: OSI Approved :: MIT License
Classifier: Operating System :: OS Independent
Requires-Python: >=3.9
License-File: LICENSE
Requires-Dist: numpy
Requires-Dist: matplotlib
Requires-Dist: scikit-learn
Requires-Dist: xgboost
Requires-Dist: scipy
Requires-Dist: pandas >=2.1.0
Requires-Dist: tiktoken
Requires-Dist: openai >=1.3.3
Requires-Dist: tenacity
Requires-Dist: jellyfish
Requires-Dist: pyyaml
